aio_agents/__init__.py
aio_agents/config.py
aio_agents/data/__init__.py
aio_agents/data/models.py
aio_agents/data/schemas.py
aio_agents/helpers/__init__.py
aio_agents/helpers/audio.py
aio_agents/helpers/blocks.py
aio_agents/helpers/chains.py
aio_agents/helpers/loaders.py
aio_agents/helpers/markdown.py
aio_agents/helpers/prompts.py
aio_agents/routes/__init__.py
aio_agents/routes/chat.py
aio_agents/routes/load.py
aio_agents/routes/payment.py
aio_agents/schemas/__init__.py
aio_agents/schemas/aws_ml.py
aio_agents/schemas/openai.py
aio_agents/schemas/pinecone.py
aio_agents/schemas/typedefs.py
aio_agents/services/__init__.py
aio_agents/services/auth.py
aio_agents/services/openai.py
aio_agents/services/pinecone.py
aio_agents/tasks/__init__.py
aio_agents/tasks/background.py
aio_agents/tasks/pubsub.py
aio_agents/tools/__init__.py
aio_agents/tools/content.py
aio_agents/tools/docker_api.py
aio_agents/tools/google_search.py
aio_agents/tools/image_gen.py
aio_agents/tools/ses_email.py
aio_agents/utils.py
aio_agents-0.0.2.dist-info/METADATA
aio_agents-0.0.2.dist-info/WHEEL
aio_agents-0.0.2.dist-info/RECORD
